mozperftest_tools/__init__.py
mozperftest_tools/lull_scheduler.py
mozperftest_tools/profile_enhancer.py
mozperftest_tools/regression_detector.py
mozperftest_tools/side_by_side.py
mozperftest_tools/utils/__init__.py
mozperftest_tools/utils/artifact_downloader.py
mozperftest_tools/utils/task_processor.py
mozperftest_tools/utils/utils.py
mozperftest_tools-0.4.3.dist-info/LICENSE.md
mozperftest_tools-0.4.3.dist-info/METADATA
mozperftest_tools-0.4.3.dist-info/WHEEL
mozperftest_tools-0.4.3.dist-info/top_level.txt
mozperftest_tools-0.4.3.dist-info/RECORD
