Metadata-Version: 2.1
Name: mozperftest_tools
Version: 0.4.3
Summary: This repository is a collection of various tools that are useful forthe things we do in Performance and Performance Testing. 
Home-page: https://github.com/mozilla/mozperftest-tools
Author: Firefox Performance Test Engineering team
Author-email: perftest@mozilla.com
Project-URL: Bug Tracker, https://github.com/mozilla/mozperftest-tools/issues
Keywords: mozilla
Classifier: Programming Language :: Python :: 3
Classifier: License :: OSI Approved :: MIT License
Classifier: Operating System :: OS Independent
Requires-Python: >=3.6
License-File: /home/sparky/mozilla-source/mozperftest-tools/LICENSE.md
Requires-Dist: requests
Requires-Dist: opencv-python ==4.5.4.60 ; python_version <= "3.7"
Requires-Dist: numpy <1.21 ; python_version <= "3.7"
Requires-Dist: scipy <1.8 ; python_version <= "3.7"
Requires-Dist: opencv-python ==4.8.1.78 ; python_version >= "3.8"
Requires-Dist: numpy >=1.23.5 ; python_version >= "3.8"
Requires-Dist: scipy ==1.10.0 ; python_version >= "3.8"
